{
  "status": "success",
  "name": "CricHD Live Channels",
  "owner": "Monirul Islam",
  "channels_amount": 42,
  "Last_update": "2026-05-05",
  "response": [
    {
      "id": "star1in",
      "title": "Star Sports 1",
      "logo": "https://sm-live-tv-channel-logo.pages.dev/CricHD/Sports/16-exptv.png",
      "url": "https://n100.zohanayaan.com:1686/hls/star1in.m3u8?md5=2A2WVmrTDqRdSo7Vcopfrw&expires=1778018497",
      "Referer": "https://executeandship.com/"
    },
    {
      "id": "starhindi",
      "title": "Star Sports 1 Hindi",
      "logo": "https://sm-live-tv-channel-logo.pages.dev/CricHD/Sports/1-exptv.png",
      "url": "https://n100.zohanayaan.com:1686/hls/starhindi.m3u8?md5=8S9GZvEB4CcQtlcTTpiLmg&expires=1778018498",
      "Referer": "https://executeandship.com/"
    },
    {
      "id": "ptvpk",
      "title": "PTV Sports",
      "logo": "https://sm-live-tv-channel-logo.pages.dev/CricHD/Sports/20-exptv.png",
      "url": "https://n100.zohanayaan.com:1686/hls/ptvpk.m3u8?md5=63CRP_n25Y_HtZF5SztFqA&expires=1778018498",
      "Referer": "https://executeandship.com/"
    },
    {
      "id": "willowusa",
      "title": "Willow HD",
      "logo": "https://sm-live-tv-channel-logo.pages.dev/CricHD/Sports/38-exptv.png",
      "url": "https://n100.zohanayaan.com:1686/hls/willowusa.m3u8?md5=fxYmndi9TqOuNL2GL9IdvA&expires=1778018498",
      "Referer": "https://executeandship.com/"
    },
    {
      "id": "willowextra",
      "title": "Willow HD 2",
      "logo": "https://sm-live-tv-channel-logo.pages.dev/CricHD/Sports/8-exptv.png",
      "url": "https://n100.zohanayaan.com:1686/hls/willowextra.m3u8?md5=ft_gCPwmwITPt4tuGukkTQ&expires=1778018498",
      "Referer": "https://executeandship.com/"
    },
    {
      "id": "tenspk",
      "title": "Ten Sports",
      "logo": "https://sm-live-tv-channel-logo.pages.dev/CricHD/Sports/10-exptv.png",
      "url": "https://n100.zohanayaan.com:1686/hls/tenspk.m3u8?md5=b_t8t-rnJMfmG9hZu4SRSA&expires=1778018498",
      "Referer": "https://executeandship.com/"
    },
    {
      "id": "asportshd",
      "title": "A Sports HD",
      "logo": "https://sm-live-tv-channel-logo.pages.dev/CricHD/Sports/12-exptv.png",
      "url": "https://n100.zohanayaan.com:1686/hls/asportshd.m3u8?md5=ZuD_dQ4OgaSjZcmYMIHPMw&expires=1778018498",
      "Referer": "https://executeandship.com/"
    },
    {
      "id": "skyscric",
      "title": "Sky Sports Cricket",
      "logo": "https://sm-live-tv-channel-logo.pages.dev/CricHD/Sports/9-exptv.png",
      "url": "https://n100.zohanayaan.com:1686/hls/skyscric.m3u8?md5=rCAi73ncRVcDXBuBwHpZHw&expires=1778018499",
      "Referer": "https://executeandship.com/"
    },
    {
      "id": "skysme",
      "title": "Sky Cinema",
      "logo": "https://sm-live-tv-channel-logo.pages.dev/CricHD/Sports/skycinema.png",
      "url": "https://n100.zohanayaan.com:1686/hls/skysme.m3u8?md5=AIiISD9fYGYJt-rhwTlzaA&expires=1778018499",
      "Referer": "https://executeandship.com/"
    },
    {
      "id": "bbtsp1",
      "title": "TNT 1",
      "logo": "https://sm-live-tv-channel-logo.pages.dev/CricHD/Sports/tnt.png",
      "url": "https://n100.zohanayaan.com:1686/hls/bbtsp1.m3u8?md5=14REwN-pqjGvFVb9sR2FyQ&expires=1778018499",
      "Referer": "https://executeandship.com/"
    },
    {
      "id": "bbtsp2",
      "title": "TNT 2",
      "logo": "https://sm-live-tv-channel-logo.pages.dev/CricHD/Sports/tnt.png",
      "url": "https://n100.zohanayaan.com:1686/hls/bbtsp2.m3u8?md5=1Qieb-ie-Aspw2Xjb2YM3Q&expires=1778018499",
      "Referer": "https://executeandship.com/"
    },
    {
      "id": "bbtsp3",
      "title": "TNT 3",
      "logo": "https://sm-live-tv-channel-logo.pages.dev/CricHD/Sports/tnt.png",
      "url": "https://n100.zohanayaan.com:1686/hls/bbtsp3.m3u8?md5=l38d0-Tic-fDyqpf7KhpVQ&expires=1778018499",
      "Referer": "https://executeandship.com/"
    },
    {
      "id": "bbtespn",
      "title": "TNT 4",
      "logo": "https://sm-live-tv-channel-logo.pages.dev/CricHD/Sports/tnt.png",
      "url": "https://n100.zohanayaan.com:1686/hls/bbtespn.m3u8?md5=CHbAO6RraA12eGyTfGtu5Q&expires=1778018499",
      "Referer": "https://executeandship.com/"
    },
    {
      "id": "sky1nz",
      "title": "Sky Sport Nz 1",
      "logo": "https://sm-live-tv-channel-logo.pages.dev/CricHD/Sports/56-exptv.png",
      "url": "https://n100.zohanayaan.com:1686/hls/sky1nz.m3u8?md5=DwnCCf5vr9776voZmpOoWg&expires=1778018500",
      "Referer": "https://executeandship.com/"
    },
    {
      "id": "sky2nz",
      "title": "Sky Sport Nz 2",
      "logo": "https://sm-live-tv-channel-logo.pages.dev/CricHD/Sports/56-exptv.png",
      "url": "https://n100.zohanayaan.com:1686/hls/sky2nz.m3u8?md5=_3qiEY3nDXg4djh1I1rOEw&expires=1778018500",
      "Referer": "https://executeandship.com/"
    },
    {
      "id": "sky3nz",
      "title": "Sky Sport Nz 3",
      "logo": "https://sm-live-tv-channel-logo.pages.dev/CricHD/Sports/56-exptv.png",
      "url": "https://n100.zohanayaan.com:1686/hls/sky3nz.m3u8?md5=QkZb7JnbYRsCzPNpdGVq_w&expires=1778018500",
      "Referer": "https://executeandship.com/"
    },
    {
      "id": "sky4nz",
      "title": "Sky Sport Nz 4",
      "logo": "https://sm-live-tv-channel-logo.pages.dev/CricHD/Sports/56-exptv.png",
      "url": "https://n100.zohanayaan.com:1686/hls/sky4nz.m3u8?md5=CIdgGjiEl2o1RoPbEup7SA&expires=1778018500",
      "Referer": "https://executeandship.com/"
    },
    {
      "id": "sky5nz",
      "title": "Sky Sport Nz 5",
      "logo": "https://sm-live-tv-channel-logo.pages.dev/CricHD/Sports/56-exptv.png",
      "url": "https://n100.zohanayaan.com:1686/hls/sky5nz.m3u8?md5=ZjrC_L_MRbyTIxkmzxSnHA&expires=1778018500",
      "Referer": "https://executeandship.com/"
    },
    {
      "id": "sky6nz",
      "title": "Sky Sport 6 Nz",
      "logo": "https://sm-live-tv-channel-logo.pages.dev/CricHD/Sports/56-exptv.png",
      "url": "https://n100.zohanayaan.com:1686/hls/sky6nz.m3u8?md5=X_tNtMRLrm6M2r6-PNDSTQ&expires=1778018500",
      "Referer": "https://executeandship.com/"
    },
    {
      "id": "sky7nz",
      "title": "Sky Sport Nz 7",
      "logo": "https://sm-live-tv-channel-logo.pages.dev/CricHD/Sports/56-exptv.png",
      "url": "https://n100.zohanayaan.com:1686/hls/sky7nz.m3u8?md5=Lx0w8Q2kacZ8c-v8ZHES7w&expires=1778018501",
      "Referer": "https://executeandship.com/"
    },
    {
      "id": "sky8nz",
      "title": "Sky Sport Nz 8",
      "logo": "https://sm-live-tv-channel-logo.pages.dev/CricHD/Sports/56-exptv.png",
      "url": "https://n100.zohanayaan.com:1686/hls/sky8nz.m3u8?md5=oABtdScluPfcCh7EoHYuKg&expires=1778018501",
      "Referer": "https://executeandship.com/"
    },
    {
      "id": "sky9nz",
      "title": "Sky Sport Nz 9",
      "logo": "https://sm-live-tv-channel-logo.pages.dev/CricHD/Sports/56-exptv.png",
      "url": "https://n100.zohanayaan.com:1686/hls/sky9nz.m3u8?md5=QZc0qajeb0pyj-sF7r2Afg&expires=1778018501",
      "Referer": "https://executeandship.com/"
    },
    {
      "id": "skysme",
      "title": "Sky Cinema",
      "logo": "https://sm-live-tv-channel-logo.pages.dev/CricHD/Sports/skycinema.png",
      "url": "https://n100.zohanayaan.com:1686/hls/skysme.m3u8?md5=vTeoqhSV7jEuyb5WACHunQ&expires=1778018501",
      "Referer": "https://executeandship.com/"
    },
    {
      "id": "skysact",
      "title": "Sky Sports Action",
      "logo": "https://sm-live-tv-channel-logo.pages.dev/CricHD/Sports/1745007829332.png",
      "url": "https://n100.zohanayaan.com:1686/hls/skysact.m3u8?md5=DZiiDa0NhMJN2a6dR2u8sg&expires=1778018501",
      "Referer": "https://executeandship.com/"
    },
    {
      "id": "skysgol",
      "title": "Sky Sports Golf",
      "logo": "https://sm-live-tv-channel-logo.pages.dev/CricHD/Sports/1745008055327.png",
      "url": "https://n100.zohanayaan.com:1686/hls/skysgol.m3u8?md5=yKyuG9Hv6LVvg2D4-Ec2dw&expires=1778018501",
      "Referer": "https://executeandship.com/"
    },
    {
      "id": "skysprem",
      "title": "Sky Sports Premier League",
      "logo": "https://sm-live-tv-channel-logo.pages.dev/CricHD/Sports/43-exptv.png",
      "url": "https://n100.zohanayaan.com:1686/hls/skysprem.m3u8?md5=koOHvaY4hur4O-IJMwMy2Q&expires=1778018501",
      "Referer": "https://executeandship.com/"
    },
    {
      "id": "skysfott",
      "title": "Sky Sports Football",
      "logo": "https://sm-live-tv-channel-logo.pages.dev/CricHD/Sports/44-exptv.png",
      "url": "https://n100.zohanayaan.com:1686/hls/skysfott.m3u8?md5=k9cfMAKI1vfOecULsjVMhA&expires=1778018501",
      "Referer": "https://executeandship.com/"
    },
    {
      "id": "skysare",
      "title": "Sky Sports Arena",
      "logo": "https://sm-live-tv-channel-logo.pages.dev/CricHD/Sports/1745007829327.png",
      "url": "https://n100.zohanayaan.com:1686/hls/skysare.m3u8?md5=GStkUECmeC9VTHMqpCM6rQ&expires=1778018502",
      "Referer": "https://executeandship.com/"
    },
    {
      "id": "skysfor1",
      "title": "Sky Sports F1",
      "logo": "https://sm-live-tv-channel-logo.pages.dev/CricHD/Sports/1745008468637.png",
      "url": "https://n100.zohanayaan.com:1686/hls/skysfor1.m3u8?md5=ior0Fz9vLkQtbEZKjVN0CA&expires=1778018502",
      "Referer": "https://executeandship.com/"
    },
    {
      "id": "laligauk",
      "title": "LaLiGA",
      "logo": "https://sm-live-tv-channel-logo.pages.dev/CricHD/Sports/19-exptv.png",
      "url": "https://n100.zohanayaan.com:1686/hls/laligauk.m3u8?md5=hd-8NUO84T-X746UlXYKuA&expires=1778018502",
      "Referer": "https://executeandship.com/"
    },
    {
      "id": "premieruk",
      "title": "Premier Sports 1",
      "logo": "https://sm-live-tv-channel-logo.pages.dev/CricHD/Sports/31-exptv.png",
      "url": "https://n100.zohanayaan.com:1686/hls/premieruk.m3u8?md5=15_iqad68F0jO9scmEYDAQ&expires=1778018502",
      "Referer": "https://executeandship.com/"
    },
    {
      "id": "hdchnl2",
      "title": "Premier Sports 2",
      "logo": "https://sm-live-tv-channel-logo.pages.dev/CricHD/Sports/31-exptv.png",
      "url": "https://n100.zohanayaan.com:1686/hls/hdchnl2.m3u8?md5=bEwuXfihMDWMCmnMcHAXRw&expires=1778018502",
      "Referer": "https://executeandship.com/"
    },
    {
      "id": "superfotball",
      "title": "Super Football",
      "logo": "https://sm-live-tv-channel-logo.pages.dev/CricHD/Sports/34-exptv.png",
      "url": "https://n100.zohanayaan.com:1686/hls/superfotball.m3u8?md5=cPX_fe_LKJ34e66c7I2uNQ&expires=1778018502",
      "Referer": "https://executeandship.com/"
    },
    {
      "id": "superpremier",
      "title": "Super Premier League",
      "logo": "https://sm-live-tv-channel-logo.pages.dev/CricHD/Sports/1745008781606.png",
      "url": "https://n100.zohanayaan.com:1686/hls/superpremier.m3u8?md5=QeMgtWzxqMaPbUpBIlTUDQ&expires=1778018502",
      "Referer": "https://executeandship.com/"
    },
    {
      "id": "fox501",
      "title": "Fox Cricket 501 HD",
      "logo": "https://sm-live-tv-channel-logo.pages.dev/CricHD/Sports/6-exptv.png",
      "url": "https://n100.zohanayaan.com:1686/hls/fox501.m3u8?md5=ovb0pcf9eWZLiPDoieEvQg&expires=1778018502",
      "Referer": "https://executeandship.com/"
    },
    {
      "id": "espnusa",
      "title": "ESPN 1",
      "logo": "https://sm-live-tv-channel-logo.pages.dev/CricHD/Sports/17-exptv.png",
      "url": "https://n100.zohanayaan.com:1686/hls/espnusa.m3u8?md5=hClv6-TBGewLXqJzhJ5SzQ&expires=1778018503",
      "Referer": "https://executeandship.com/"
    },
    {
      "id": "espn2",
      "title": "ESPN 2",
      "logo": "https://sm-live-tv-channel-logo.pages.dev/CricHD/Sports/17-exptv.png",
      "url": "https://n100.zohanayaan.com:1686/hls/espn2.m3u8?md5=pmcUqX9jeBnLUro-HzBclQ&expires=1778018503",
      "Referer": "https://executeandship.com/"
    },
    {
      "id": "skysare",
      "title": "Sky Sports Arena",
      "logo": "https://sm-live-tv-channel-logo.pages.dev/CricHD/Sports/1745007829327.png",
      "url": "https://n100.zohanayaan.com:1686/hls/skysare.m3u8?md5=Z9d9bUvkRZmRgsptnebe2A&expires=1778018503",
      "Referer": "https://executeandship.com/"
    },
    {
      "id": "skysmixx",
      "title": "Sky Sports Mix",
      "logo": "https://sm-live-tv-channel-logo.pages.dev/CricHD/Sports/13-exptv.png",
      "url": "https://n100.zohanayaan.com:1686/hls/skysmixx.m3u8?md5=-v0FuIfRLpKZwpXluZc4rQ&expires=1778018503",
      "Referer": "https://executeandship.com/"
    },
    {
      "id": "skystennis",
      "title": "Sky Sports Tennis",
      "logo": "https://sm-live-tv-channel-logo.pages.dev/CricHD/Sports/1745009085794.png",
      "url": "https://n100.zohanayaan.com:1686/hls/skystennis.m3u8?md5=ke_Vg-iMlKH5UN1i3sOI8A&expires=1778018503",
      "Referer": "https://executeandship.com/"
    },
    {
      "id": "fox501",
      "title": "Fox Cricket 501 HD",
      "logo": "https://sm-live-tv-channel-logo.pages.dev/CricHD/Sports/6-exptv.png",
      "url": "https://n100.zohanayaan.com:1686/hls/fox501.m3u8?md5=F7dvvWZFuPx8Sq0Pt3dyzg&expires=1778018503",
      "Referer": "https://executeandship.com/"
    },
    {
      "id": "ten1hd",
      "title": "Sony Sports3",
      "logo": "https://sm-live-tv-channel-logo.pages.dev/CricHD/Sports/1000173192-modified.png",
      "url": "https://n100.zohanayaan.com:1686/hls/ten1hd.m3u8?md5=cRktH33Ze7qkuPy0vFfMuQ&expires=1778018503",
      "Referer": "https://executeandship.com/"
    }
  ]
}