{
  "status": "success",
  "name": "CricHD Live Channels",
  "owner": "Monirul Islam",
  "channels_amount": 42,
  "Last_update": "2026-05-17",
  "response": [
    {
      "id": "star1in",
      "title": "Star Sports 1",
      "logo": "https://sm-live-tv-channel-logo.pages.dev/CricHD/Sports/16-exptv.png",
      "url": "https://cdn1.zohanayaan.com:1686/hls/star1in.m3u8?md5=zs--IS7Nsffwr-aXsYDZ7w&expires=1779043212",
      "Referer": "https://executeandship.com/"
    },
    {
      "id": "starhindi",
      "title": "Star Sports 1 Hindi",
      "logo": "https://sm-live-tv-channel-logo.pages.dev/CricHD/Sports/1-exptv.png",
      "url": "https://cdn9.zohanayaan.com:1686/hls/starhindi.m3u8?md5=hTbBVgy_eTUJnFpVOUsuIA&expires=1779043212",
      "Referer": "https://executeandship.com/"
    },
    {
      "id": "ptvpk",
      "title": "PTV Sports",
      "logo": "https://sm-live-tv-channel-logo.pages.dev/CricHD/Sports/20-exptv.png",
      "url": "https://cdn6.zohanayaan.com:1686/hls/ptvpk.m3u8?md5=O0n7xUGcokkP_fCEfpK3Dg&expires=1779043212",
      "Referer": "https://executeandship.com/"
    },
    {
      "id": "willowusa",
      "title": "Willow HD",
      "logo": "https://sm-live-tv-channel-logo.pages.dev/CricHD/Sports/38-exptv.png",
      "url": "https://cdn6.zohanayaan.com:1686/hls/willowusa.m3u8?md5=B7mQ6hiYIhmFvMzsYnsGpw&expires=1779043213",
      "Referer": "https://executeandship.com/"
    },
    {
      "id": "willowextra",
      "title": "Willow HD 2",
      "logo": "https://sm-live-tv-channel-logo.pages.dev/CricHD/Sports/8-exptv.png",
      "url": "https://cdn7.zohanayaan.com:1686/hls/willowextra.m3u8?md5=YFbn2CG0nxeIkcBzu8GHiw&expires=1779043213",
      "Referer": "https://executeandship.com/"
    },
    {
      "id": "tenspk",
      "title": "Ten Sports",
      "logo": "https://sm-live-tv-channel-logo.pages.dev/CricHD/Sports/10-exptv.png",
      "url": "https://cdn1.zohanayaan.com:1686/hls/tenspk.m3u8?md5=Dxict4BzF-I0SqfBaVMSTQ&expires=1779043213",
      "Referer": "https://executeandship.com/"
    },
    {
      "id": "asportshd",
      "title": "A Sports HD",
      "logo": "https://sm-live-tv-channel-logo.pages.dev/CricHD/Sports/12-exptv.png",
      "url": "https://cdn3.zohanayaan.com:1686/hls/asportshd.m3u8?md5=E5T_KrpqRmT_Bkc-trGrxQ&expires=1779043213",
      "Referer": "https://executeandship.com/"
    },
    {
      "id": "skyscric",
      "title": "Sky Sports Cricket",
      "logo": "https://sm-live-tv-channel-logo.pages.dev/CricHD/Sports/9-exptv.png",
      "url": "https://cdn9.zohanayaan.com:1686/hls/skyscric.m3u8?md5=a6MXAeEF0d-YRGkNjI8rQQ&expires=1779043213",
      "Referer": "https://executeandship.com/"
    },
    {
      "id": "skysme",
      "title": "Sky Cinema",
      "logo": "https://sm-live-tv-channel-logo.pages.dev/CricHD/Sports/skycinema.png",
      "url": "https://cdn3.zohanayaan.com:1686/hls/skysme.m3u8?md5=7-4MZw1xBttrs3rQ7TG8Eg&expires=1779043213",
      "Referer": "https://executeandship.com/"
    },
    {
      "id": "bbtsp1",
      "title": "TNT 1",
      "logo": "https://sm-live-tv-channel-logo.pages.dev/CricHD/Sports/tnt.png",
      "url": "https://cdn8.zohanayaan.com:1686/hls/bbtsp1.m3u8?md5=Ik9gr4VCZWEhRZs3s99uWg&expires=1779043214",
      "Referer": "https://executeandship.com/"
    },
    {
      "id": "bbtsp2",
      "title": "TNT 2",
      "logo": "https://sm-live-tv-channel-logo.pages.dev/CricHD/Sports/tnt.png",
      "url": "https://cdn10.zohanayaan.com:1686/hls/bbtsp2.m3u8?md5=vXL87IiuoEwlIK-HaQDNJA&expires=1779043214",
      "Referer": "https://executeandship.com/"
    },
    {
      "id": "bbtsp3",
      "title": "TNT 3",
      "logo": "https://sm-live-tv-channel-logo.pages.dev/CricHD/Sports/tnt.png",
      "url": "https://cdn1.zohanayaan.com:1686/hls/bbtsp3.m3u8?md5=7H3XyGrWS9SZ8a9ab_WAYw&expires=1779043214",
      "Referer": "https://executeandship.com/"
    },
    {
      "id": "bbtespn",
      "title": "TNT 4",
      "logo": "https://sm-live-tv-channel-logo.pages.dev/CricHD/Sports/tnt.png",
      "url": "https://cdn9.zohanayaan.com:1686/hls/bbtespn.m3u8?md5=1NnxCj3gWF_7GptjmC0i4w&expires=1779043214",
      "Referer": "https://executeandship.com/"
    },
    {
      "id": "sky1nz",
      "title": "Sky Sport Nz 1",
      "logo": "https://sm-live-tv-channel-logo.pages.dev/CricHD/Sports/56-exptv.png",
      "url": "https://cdn8.zohanayaan.com:1686/hls/sky1nz.m3u8?md5=AV2N_0F1YkfYfILuNuSyGA&expires=1779043214",
      "Referer": "https://executeandship.com/"
    },
    {
      "id": "sky2nz",
      "title": "Sky Sport Nz 2",
      "logo": "https://sm-live-tv-channel-logo.pages.dev/CricHD/Sports/56-exptv.png",
      "url": "https://cdn6.zohanayaan.com:1686/hls/sky2nz.m3u8?md5=KH70CD49fhIstorU_tyGYA&expires=1779043214",
      "Referer": "https://executeandship.com/"
    },
    {
      "id": "sky3nz",
      "title": "Sky Sport Nz 3",
      "logo": "https://sm-live-tv-channel-logo.pages.dev/CricHD/Sports/56-exptv.png",
      "url": "https://cdn1.zohanayaan.com:1686/hls/sky3nz.m3u8?md5=6L9ZAodm1SMYN2mmKvJwgw&expires=1779043214",
      "Referer": "https://executeandship.com/"
    },
    {
      "id": "sky4nz",
      "title": "Sky Sport Nz 4",
      "logo": "https://sm-live-tv-channel-logo.pages.dev/CricHD/Sports/56-exptv.png",
      "url": "https://cdn5.zohanayaan.com:1686/hls/sky4nz.m3u8?md5=ZJgFjSrVE1XRFgECvRO7DA&expires=1779043214",
      "Referer": "https://executeandship.com/"
    },
    {
      "id": "sky5nz",
      "title": "Sky Sport Nz 5",
      "logo": "https://sm-live-tv-channel-logo.pages.dev/CricHD/Sports/56-exptv.png",
      "url": "https://cdn9.zohanayaan.com:1686/hls/sky5nz.m3u8?md5=7fnHcnlr75NKVkDB-QED9w&expires=1779043214",
      "Referer": "https://executeandship.com/"
    },
    {
      "id": "sky6nz",
      "title": "Sky Sport 6 Nz",
      "logo": "https://sm-live-tv-channel-logo.pages.dev/CricHD/Sports/56-exptv.png",
      "url": "https://cdn3.zohanayaan.com:1686/hls/sky6nz.m3u8?md5=57i6hdWcStHuiGnZAxIKnA&expires=1779043215",
      "Referer": "https://executeandship.com/"
    },
    {
      "id": "sky7nz",
      "title": "Sky Sport Nz 7",
      "logo": "https://sm-live-tv-channel-logo.pages.dev/CricHD/Sports/56-exptv.png",
      "url": "https://cdn6.zohanayaan.com:1686/hls/sky7nz.m3u8?md5=ORkmOExQgpWUTJf9toN47A&expires=1779043215",
      "Referer": "https://executeandship.com/"
    },
    {
      "id": "sky8nz",
      "title": "Sky Sport Nz 8",
      "logo": "https://sm-live-tv-channel-logo.pages.dev/CricHD/Sports/56-exptv.png",
      "url": "https://cdn8.zohanayaan.com:1686/hls/sky8nz.m3u8?md5=On2UpV4OyJko5RGuM15KLQ&expires=1779043215",
      "Referer": "https://executeandship.com/"
    },
    {
      "id": "sky9nz",
      "title": "Sky Sport Nz 9",
      "logo": "https://sm-live-tv-channel-logo.pages.dev/CricHD/Sports/56-exptv.png",
      "url": "https://cdn6.zohanayaan.com:1686/hls/sky9nz.m3u8?md5=D-oozI4KWuZPoN9hcw-gpw&expires=1779043215",
      "Referer": "https://executeandship.com/"
    },
    {
      "id": "skysme",
      "title": "Sky Cinema",
      "logo": "https://sm-live-tv-channel-logo.pages.dev/CricHD/Sports/skycinema.png",
      "url": "https://cdn8.zohanayaan.com:1686/hls/skysme.m3u8?md5=NifTIJyxfp0wmhUyfqqLRA&expires=1779043215",
      "Referer": "https://executeandship.com/"
    },
    {
      "id": "skysact",
      "title": "Sky Sports Action",
      "logo": "https://sm-live-tv-channel-logo.pages.dev/CricHD/Sports/1745007829332.png",
      "url": "https://cdn5.zohanayaan.com:1686/hls/skysact.m3u8?md5=48De40kcoq_up4zb3dUP_w&expires=1779043215",
      "Referer": "https://executeandship.com/"
    },
    {
      "id": "skysgol",
      "title": "Sky Sports Golf",
      "logo": "https://sm-live-tv-channel-logo.pages.dev/CricHD/Sports/1745008055327.png",
      "url": "https://cdn7.zohanayaan.com:1686/hls/skysgol.m3u8?md5=vlTU6ItXS17YnG-2omtF0g&expires=1779043215",
      "Referer": "https://executeandship.com/"
    },
    {
      "id": "skysprem",
      "title": "Sky Sports Premier League",
      "logo": "https://sm-live-tv-channel-logo.pages.dev/CricHD/Sports/43-exptv.png",
      "url": "https://cdn6.zohanayaan.com:1686/hls/skysprem.m3u8?md5=yDJ0p3ZzHgZ9sRGDXWnI5A&expires=1779043216",
      "Referer": "https://executeandship.com/"
    },
    {
      "id": "skysfott",
      "title": "Sky Sports Football",
      "logo": "https://sm-live-tv-channel-logo.pages.dev/CricHD/Sports/44-exptv.png",
      "url": "https://cdn5.zohanayaan.com:1686/hls/skysfott.m3u8?md5=zMuIdUaDRoxVsZ0bNz1knw&expires=1779043216",
      "Referer": "https://executeandship.com/"
    },
    {
      "id": "skysare",
      "title": "Sky Sports Arena",
      "logo": "https://sm-live-tv-channel-logo.pages.dev/CricHD/Sports/1745007829327.png",
      "url": "https://cdn10.zohanayaan.com:1686/hls/skysare.m3u8?md5=12wpmyJKVfXkVYYpRTzJZw&expires=1779043216",
      "Referer": "https://executeandship.com/"
    },
    {
      "id": "skysfor1",
      "title": "Sky Sports F1",
      "logo": "https://sm-live-tv-channel-logo.pages.dev/CricHD/Sports/1745008468637.png",
      "url": "https://cdn4.zohanayaan.com:1686/hls/skysfor1.m3u8?md5=bVJbTQ8fn2lhlO3C-o7TZA&expires=1779043216",
      "Referer": "https://executeandship.com/"
    },
    {
      "id": "laligauk",
      "title": "LaLiGA",
      "logo": "https://sm-live-tv-channel-logo.pages.dev/CricHD/Sports/19-exptv.png",
      "url": "https://cdn4.zohanayaan.com:1686/hls/laligauk.m3u8?md5=CQXHeSjGuejI1ltaVSeEmw&expires=1779043216",
      "Referer": "https://executeandship.com/"
    },
    {
      "id": "premieruk",
      "title": "Premier Sports 1",
      "logo": "https://sm-live-tv-channel-logo.pages.dev/CricHD/Sports/31-exptv.png",
      "url": "https://cdn3.zohanayaan.com:1686/hls/premieruk.m3u8?md5=9069-Uck8P7KFSDxLXiguA&expires=1779043216",
      "Referer": "https://executeandship.com/"
    },
    {
      "id": "hdchnl2",
      "title": "Premier Sports 2",
      "logo": "https://sm-live-tv-channel-logo.pages.dev/CricHD/Sports/31-exptv.png",
      "url": "https://cdn10.zohanayaan.com:1686/hls/hdchnl2.m3u8?md5=kUz2fhhMiwuV-Gh-QIaZrA&expires=1779043216",
      "Referer": "https://executeandship.com/"
    },
    {
      "id": "superfotball",
      "title": "Super Football",
      "logo": "https://sm-live-tv-channel-logo.pages.dev/CricHD/Sports/34-exptv.png",
      "url": "https://cdn3.zohanayaan.com:1686/hls/superfotball.m3u8?md5=Ku73ebZSLEb4_67rCC7qBA&expires=1779043216",
      "Referer": "https://executeandship.com/"
    },
    {
      "id": "superpremier",
      "title": "Super Premier League",
      "logo": "https://sm-live-tv-channel-logo.pages.dev/CricHD/Sports/1745008781606.png",
      "url": "https://cdn3.zohanayaan.com:1686/hls/superpremier.m3u8?md5=GzYpUXcl9f7ybc-FovN8yA&expires=1779043217",
      "Referer": "https://executeandship.com/"
    },
    {
      "id": "fox501",
      "title": "Fox Cricket 501 HD",
      "logo": "https://sm-live-tv-channel-logo.pages.dev/CricHD/Sports/6-exptv.png",
      "url": "https://cdn6.zohanayaan.com:1686/hls/fox501.m3u8?md5=oxP6ZwK4TD_JqRdM1-hVeg&expires=1779043217",
      "Referer": "https://executeandship.com/"
    },
    {
      "id": "espnusa",
      "title": "ESPN 1",
      "logo": "https://sm-live-tv-channel-logo.pages.dev/CricHD/Sports/17-exptv.png",
      "url": "https://cdn1.zohanayaan.com:1686/hls/espnusa.m3u8?md5=6GIge-lxRv6kcLkjLpk7Fg&expires=1779043217",
      "Referer": "https://executeandship.com/"
    },
    {
      "id": "espn2",
      "title": "ESPN 2",
      "logo": "https://sm-live-tv-channel-logo.pages.dev/CricHD/Sports/17-exptv.png",
      "url": "https://cdn10.zohanayaan.com:1686/hls/espn2.m3u8?md5=cr1Wp3Zu8KL8G6eo-vtVkg&expires=1779043217",
      "Referer": "https://executeandship.com/"
    },
    {
      "id": "skysare",
      "title": "Sky Sports Arena",
      "logo": "https://sm-live-tv-channel-logo.pages.dev/CricHD/Sports/1745007829327.png",
      "url": "https://cdn7.zohanayaan.com:1686/hls/skysare.m3u8?md5=UxovoGG301JQTqi7DEud2w&expires=1779043217",
      "Referer": "https://executeandship.com/"
    },
    {
      "id": "skysmixx",
      "title": "Sky Sports Mix",
      "logo": "https://sm-live-tv-channel-logo.pages.dev/CricHD/Sports/13-exptv.png",
      "url": "https://cdn1.zohanayaan.com:1686/hls/skysmixx.m3u8?md5=kxFedhAtho1no4vHJpNg1A&expires=1779043217",
      "Referer": "https://executeandship.com/"
    },
    {
      "id": "skystennis",
      "title": "Sky Sports Tennis",
      "logo": "https://sm-live-tv-channel-logo.pages.dev/CricHD/Sports/1745009085794.png",
      "url": "https://cdn10.zohanayaan.com:1686/hls/skystennis.m3u8?md5=nUGEOGfIqTJKO6WIglKWGQ&expires=1779043217",
      "Referer": "https://executeandship.com/"
    },
    {
      "id": "fox501",
      "title": "Fox Cricket 501 HD",
      "logo": "https://sm-live-tv-channel-logo.pages.dev/CricHD/Sports/6-exptv.png",
      "url": "https://cdn5.zohanayaan.com:1686/hls/fox501.m3u8?md5=oxP6ZwK4TD_JqRdM1-hVeg&expires=1779043217",
      "Referer": "https://executeandship.com/"
    },
    {
      "id": "ten1hd",
      "title": "Sony Sports3",
      "logo": "https://sm-live-tv-channel-logo.pages.dev/CricHD/Sports/1000173192-modified.png",
      "url": "https://cdn5.zohanayaan.com:1686/hls/ten1hd.m3u8?md5=gkg5o3eVprYO_E_NPo3m3w&expires=1779043217",
      "Referer": "https://executeandship.com/"
    }
  ]
}