{
  "status": "success",
  "name": "CricHD Live Channels",
  "owner": "Monirul Islam",
  "channels_amount": 42,
  "Last_update": "2026-06-01",
  "response": [
    {
      "id": "star1in",
      "title": "Star Sports 1",
      "logo": "https://sm-live-tv-channel-logo.pages.dev/CricHD/Sports/16-exptv.png",
      "url": "https://cdn1.zohanayaan.com:1686/hls/star1in.m3u8?md5=ffZtHp01Ti0bITXj39sWDw&expires=1780294815",
      "Referer": "https://executeandship.com/"
    },
    {
      "id": "starhindi",
      "title": "Star Sports 1 Hindi",
      "logo": "https://sm-live-tv-channel-logo.pages.dev/CricHD/Sports/1-exptv.png",
      "url": "https://cdn3.zohanayaan.com:1686/hls/starhindi.m3u8?md5=Hhkno-FNLwv_oexFFH2Z3w&expires=1780294815",
      "Referer": "https://executeandship.com/"
    },
    {
      "id": "ptvpk",
      "title": "PTV Sports",
      "logo": "https://sm-live-tv-channel-logo.pages.dev/CricHD/Sports/20-exptv.png",
      "url": "https://cdn1.zohanayaan.com:1686/hls/ptvpk.m3u8?md5=b5QklaTvWC_vhDYX4eYSjw&expires=1780294815",
      "Referer": "https://executeandship.com/"
    },
    {
      "id": "willowusa",
      "title": "Willow HD",
      "logo": "https://sm-live-tv-channel-logo.pages.dev/CricHD/Sports/38-exptv.png",
      "url": "https://cdn3.zohanayaan.com:1686/hls/willowusa.m3u8?md5=-Qub8NGXDLHjVtiH_TbVVw&expires=1780294815",
      "Referer": "https://executeandship.com/"
    },
    {
      "id": "willowextra",
      "title": "Willow HD 2",
      "logo": "https://sm-live-tv-channel-logo.pages.dev/CricHD/Sports/8-exptv.png",
      "url": "https://cdn5.zohanayaan.com:1686/hls/willowextra.m3u8?md5=AOQ8y3hhA9XuvOOw9B9S_g&expires=1780294816",
      "Referer": "https://executeandship.com/"
    },
    {
      "id": "tenspk",
      "title": "Ten Sports",
      "logo": "https://sm-live-tv-channel-logo.pages.dev/CricHD/Sports/10-exptv.png",
      "url": "https://cdn3.zohanayaan.com:1686/hls/tenspk.m3u8?md5=Gl_kxtWW6DmC3qPoDiggQA&expires=1780294816",
      "Referer": "https://executeandship.com/"
    },
    {
      "id": "asportshd",
      "title": "A Sports HD",
      "logo": "https://sm-live-tv-channel-logo.pages.dev/CricHD/Sports/12-exptv.png",
      "url": "https://cdn9.zohanayaan.com:1686/hls/asportshd.m3u8?md5=0ylc0y6C3AIYdLs-P5EEZw&expires=1780294816",
      "Referer": "https://executeandship.com/"
    },
    {
      "id": "skyscric",
      "title": "Sky Sports Cricket",
      "logo": "https://sm-live-tv-channel-logo.pages.dev/CricHD/Sports/9-exptv.png",
      "url": "https://cdn8.zohanayaan.com:1686/hls/skyscric.m3u8?md5=nd2PKVFFQ0ZnWgRc3ytxHQ&expires=1780294816",
      "Referer": "https://executeandship.com/"
    },
    {
      "id": "skysme",
      "title": "Sky Cinema",
      "logo": "https://sm-live-tv-channel-logo.pages.dev/CricHD/Sports/skycinema.png",
      "url": "https://cdn4.zohanayaan.com:1686/hls/skysme.m3u8?md5=5vU9RenGUSTPDXfctFipMQ&expires=1780294817",
      "Referer": "https://executeandship.com/"
    },
    {
      "id": "bbtsp1",
      "title": "TNT 1",
      "logo": "https://sm-live-tv-channel-logo.pages.dev/CricHD/Sports/tnt.png",
      "url": "https://cdn6.zohanayaan.com:1686/hls/bbtsp1.m3u8?md5=K6nEho_GZjKwhwZLNXrSBA&expires=1780294817",
      "Referer": "https://executeandship.com/"
    },
    {
      "id": "bbtsp2",
      "title": "TNT 2",
      "logo": "https://sm-live-tv-channel-logo.pages.dev/CricHD/Sports/tnt.png",
      "url": "https://cdn4.zohanayaan.com:1686/hls/bbtsp2.m3u8?md5=JzoYsi8STWt8RA1t5smybg&expires=1780294817",
      "Referer": "https://executeandship.com/"
    },
    {
      "id": "bbtsp3",
      "title": "TNT 3",
      "logo": "https://sm-live-tv-channel-logo.pages.dev/CricHD/Sports/tnt.png",
      "url": "https://cdn1.zohanayaan.com:1686/hls/bbtsp3.m3u8?md5=SO1vsp1g2isVwxWxTXu8_w&expires=1780294817",
      "Referer": "https://executeandship.com/"
    },
    {
      "id": "bbtespn",
      "title": "TNT 4",
      "logo": "https://sm-live-tv-channel-logo.pages.dev/CricHD/Sports/tnt.png",
      "url": "https://cdn6.zohanayaan.com:1686/hls/bbtespn.m3u8?md5=xj2qY7b7sCENHx1diSTSLA&expires=1780294817",
      "Referer": "https://executeandship.com/"
    },
    {
      "id": "sky1nz",
      "title": "Sky Sport Nz 1",
      "logo": "https://sm-live-tv-channel-logo.pages.dev/CricHD/Sports/56-exptv.png",
      "url": "https://cdn9.zohanayaan.com:1686/hls/sky1nz.m3u8?md5=dZkmgbXd3Oll-hegFgO6Hg&expires=1780294818",
      "Referer": "https://executeandship.com/"
    },
    {
      "id": "sky2nz",
      "title": "Sky Sport Nz 2",
      "logo": "https://sm-live-tv-channel-logo.pages.dev/CricHD/Sports/56-exptv.png",
      "url": "https://cdn2.zohanayaan.com:1686/hls/sky2nz.m3u8?md5=AXxIllGm9dj-ccTqTDAPAw&expires=1780294818",
      "Referer": "https://executeandship.com/"
    },
    {
      "id": "sky3nz",
      "title": "Sky Sport Nz 3",
      "logo": "https://sm-live-tv-channel-logo.pages.dev/CricHD/Sports/56-exptv.png",
      "url": "https://cdn8.zohanayaan.com:1686/hls/sky3nz.m3u8?md5=PTJF0DQ5GjC-joa1xHGebA&expires=1780294818",
      "Referer": "https://executeandship.com/"
    },
    {
      "id": "sky4nz",
      "title": "Sky Sport Nz 4",
      "logo": "https://sm-live-tv-channel-logo.pages.dev/CricHD/Sports/56-exptv.png",
      "url": "https://cdn4.zohanayaan.com:1686/hls/sky4nz.m3u8?md5=0PxsdQMfld0xWXTdhht8Lg&expires=1780294818",
      "Referer": "https://executeandship.com/"
    },
    {
      "id": "sky5nz",
      "title": "Sky Sport Nz 5",
      "logo": "https://sm-live-tv-channel-logo.pages.dev/CricHD/Sports/56-exptv.png",
      "url": "https://cdn10.zohanayaan.com:1686/hls/sky5nz.m3u8?md5=tZVFJn_CUStzYBa8dbMwTA&expires=1780294818",
      "Referer": "https://executeandship.com/"
    },
    {
      "id": "sky6nz",
      "title": "Sky Sport 6 Nz",
      "logo": "https://sm-live-tv-channel-logo.pages.dev/CricHD/Sports/56-exptv.png",
      "url": "https://cdn8.zohanayaan.com:1686/hls/sky6nz.m3u8?md5=wQD8eKLKMYVzgmsyYmq3ww&expires=1780294819",
      "Referer": "https://executeandship.com/"
    },
    {
      "id": "sky7nz",
      "title": "Sky Sport Nz 7",
      "logo": "https://sm-live-tv-channel-logo.pages.dev/CricHD/Sports/56-exptv.png",
      "url": "https://cdn3.zohanayaan.com:1686/hls/sky7nz.m3u8?md5=PyEoRdy2pZ-pwdeBpMo6yQ&expires=1780294819",
      "Referer": "https://executeandship.com/"
    },
    {
      "id": "sky8nz",
      "title": "Sky Sport Nz 8",
      "logo": "https://sm-live-tv-channel-logo.pages.dev/CricHD/Sports/56-exptv.png",
      "url": "https://cdn3.zohanayaan.com:1686/hls/sky8nz.m3u8?md5=WY3F0wP1eRV_Xro-DzaDfA&expires=1780294819",
      "Referer": "https://executeandship.com/"
    },
    {
      "id": "sky9nz",
      "title": "Sky Sport Nz 9",
      "logo": "https://sm-live-tv-channel-logo.pages.dev/CricHD/Sports/56-exptv.png",
      "url": "https://cdn7.zohanayaan.com:1686/hls/sky9nz.m3u8?md5=KeRenJIerNkktBfrOjPmnw&expires=1780294819",
      "Referer": "https://executeandship.com/"
    },
    {
      "id": "skysme",
      "title": "Sky Cinema",
      "logo": "https://sm-live-tv-channel-logo.pages.dev/CricHD/Sports/skycinema.png",
      "url": "https://cdn5.zohanayaan.com:1686/hls/skysme.m3u8?md5=Yap4ngNLG5XySMfj-UADjw&expires=1780294819",
      "Referer": "https://executeandship.com/"
    },
    {
      "id": "skysact",
      "title": "Sky Sports Action",
      "logo": "https://sm-live-tv-channel-logo.pages.dev/CricHD/Sports/1745007829332.png",
      "url": "https://cdn4.zohanayaan.com:1686/hls/skysact.m3u8?md5=NybTrEBNkwAlG1yJxDN6Ow&expires=1780294819",
      "Referer": "https://executeandship.com/"
    },
    {
      "id": "skysgol",
      "title": "Sky Sports Golf",
      "logo": "https://sm-live-tv-channel-logo.pages.dev/CricHD/Sports/1745008055327.png",
      "url": "https://cdn3.zohanayaan.com:1686/hls/skysgol.m3u8?md5=y1fYMRgjaLtrMeLJjpxXFA&expires=1780294819",
      "Referer": "https://executeandship.com/"
    },
    {
      "id": "skysprem",
      "title": "Sky Sports Premier League",
      "logo": "https://sm-live-tv-channel-logo.pages.dev/CricHD/Sports/43-exptv.png",
      "url": "https://cdn5.zohanayaan.com:1686/hls/skysprem.m3u8?md5=3ImuTGw-arBcY4WgVQrOPw&expires=1780294820",
      "Referer": "https://executeandship.com/"
    },
    {
      "id": "skysfott",
      "title": "Sky Sports Football",
      "logo": "https://sm-live-tv-channel-logo.pages.dev/CricHD/Sports/44-exptv.png",
      "url": "https://cdn6.zohanayaan.com:1686/hls/skysfott.m3u8?md5=4e6DYxHy9tv5RnMZ2fk-5Q&expires=1780294820",
      "Referer": "https://executeandship.com/"
    },
    {
      "id": "skysare",
      "title": "Sky Sports Arena",
      "logo": "https://sm-live-tv-channel-logo.pages.dev/CricHD/Sports/1745007829327.png",
      "url": "https://cdn5.zohanayaan.com:1686/hls/skysare.m3u8?md5=M608EUFCFCn9TWAO_FunwA&expires=1780294820",
      "Referer": "https://executeandship.com/"
    },
    {
      "id": "skysfor1",
      "title": "Sky Sports F1",
      "logo": "https://sm-live-tv-channel-logo.pages.dev/CricHD/Sports/1745008468637.png",
      "url": "https://cdn4.zohanayaan.com:1686/hls/skysfor1.m3u8?md5=rUQAEOyPp9eoZapmVwaZSA&expires=1780294820",
      "Referer": "https://executeandship.com/"
    },
    {
      "id": "laligauk",
      "title": "LaLiGA",
      "logo": "https://sm-live-tv-channel-logo.pages.dev/CricHD/Sports/19-exptv.png",
      "url": "https://cdn5.zohanayaan.com:1686/hls/laligauk.m3u8?md5=sD9xbzB8X_4XSO3_15dXbw&expires=1780294820",
      "Referer": "https://executeandship.com/"
    },
    {
      "id": "premieruk",
      "title": "Premier Sports 1",
      "logo": "https://sm-live-tv-channel-logo.pages.dev/CricHD/Sports/31-exptv.png",
      "url": "https://cdn9.zohanayaan.com:1686/hls/premieruk.m3u8?md5=MwisACcrmyukX4vTpsxUpA&expires=1780294820",
      "Referer": "https://executeandship.com/"
    },
    {
      "id": "hdchnl2",
      "title": "Premier Sports 2",
      "logo": "https://sm-live-tv-channel-logo.pages.dev/CricHD/Sports/31-exptv.png",
      "url": "https://cdn1.zohanayaan.com:1686/hls/hdchnl2.m3u8?md5=JLwXW0aAokDQcNZSHS157w&expires=1780294820",
      "Referer": "https://executeandship.com/"
    },
    {
      "id": "superfotball",
      "title": "Super Football",
      "logo": "https://sm-live-tv-channel-logo.pages.dev/CricHD/Sports/34-exptv.png",
      "url": "https://cdn5.zohanayaan.com:1686/hls/superfotball.m3u8?md5=2yppaNSod4cSx2Jpx611og&expires=1780294821",
      "Referer": "https://executeandship.com/"
    },
    {
      "id": "superpremier",
      "title": "Super Premier League",
      "logo": "https://sm-live-tv-channel-logo.pages.dev/CricHD/Sports/1745008781606.png",
      "url": "https://cdn10.zohanayaan.com:1686/hls/superpremier.m3u8?md5=D8churV6z2m-FNVYWCd1pQ&expires=1780294821",
      "Referer": "https://executeandship.com/"
    },
    {
      "id": "fox501",
      "title": "Fox Cricket 501 HD",
      "logo": "https://sm-live-tv-channel-logo.pages.dev/CricHD/Sports/6-exptv.png",
      "url": "https://cdn1.zohanayaan.com:1686/hls/fox501.m3u8?md5=tDiNmQz02G3IX6hXuZUFag&expires=1780294821",
      "Referer": "https://executeandship.com/"
    },
    {
      "id": "espnusa",
      "title": "ESPN 1",
      "logo": "https://sm-live-tv-channel-logo.pages.dev/CricHD/Sports/17-exptv.png",
      "url": "https://cdn2.zohanayaan.com:1686/hls/espnusa.m3u8?md5=yEsp9eRv6v8EAsms1ehRSQ&expires=1780294821",
      "Referer": "https://executeandship.com/"
    },
    {
      "id": "espn2",
      "title": "ESPN 2",
      "logo": "https://sm-live-tv-channel-logo.pages.dev/CricHD/Sports/17-exptv.png",
      "url": "https://cdn10.zohanayaan.com:1686/hls/espn2.m3u8?md5=6KOxU4kou8twRHllkWBI9A&expires=1780294821",
      "Referer": "https://executeandship.com/"
    },
    {
      "id": "skysare",
      "title": "Sky Sports Arena",
      "logo": "https://sm-live-tv-channel-logo.pages.dev/CricHD/Sports/1745007829327.png",
      "url": "https://cdn9.zohanayaan.com:1686/hls/skysare.m3u8?md5=FsLA_wZ4L8y-wa9Jir_wFw&expires=1780294821",
      "Referer": "https://executeandship.com/"
    },
    {
      "id": "skysmixx",
      "title": "Sky Sports Mix",
      "logo": "https://sm-live-tv-channel-logo.pages.dev/CricHD/Sports/13-exptv.png",
      "url": "https://cdn7.zohanayaan.com:1686/hls/skysmixx.m3u8?md5=LZcpbKW11vcO_morDNcnPw&expires=1780294822",
      "Referer": "https://executeandship.com/"
    },
    {
      "id": "skystennis",
      "title": "Sky Sports Tennis",
      "logo": "https://sm-live-tv-channel-logo.pages.dev/CricHD/Sports/1745009085794.png",
      "url": "https://cdn6.zohanayaan.com:1686/hls/skystennis.m3u8?md5=69nMbrdy9X7yePiT9p5EAA&expires=1780294822",
      "Referer": "https://executeandship.com/"
    },
    {
      "id": "fox501",
      "title": "Fox Cricket 501 HD",
      "logo": "https://sm-live-tv-channel-logo.pages.dev/CricHD/Sports/6-exptv.png",
      "url": "https://cdn5.zohanayaan.com:1686/hls/fox501.m3u8?md5=Zqf5caos1lqGA5XNYnBlPQ&expires=1780294822",
      "Referer": "https://executeandship.com/"
    },
    {
      "id": "ten1hd",
      "title": "Sony Sports3",
      "logo": "https://sm-live-tv-channel-logo.pages.dev/CricHD/Sports/1000173192-modified.png",
      "url": "https://cdn4.zohanayaan.com:1686/hls/ten1hd.m3u8?md5=q9ffhI2NQb_gKE1qTVu0AQ&expires=1780294822",
      "Referer": "https://executeandship.com/"
    }
  ]
}