{
  "status": "success",
  "name": "CricHD Live Channels",
  "owner": "Monirul Islam",
  "channels_amount": 42,
  "Last_update": "2026-06-25",
  "response": [
    {
      "id": "star1in",
      "title": "Star Sports 1",
      "logo": "https://sm-live-tv-channel-logo.pages.dev/CricHD/Sports/16-exptv.png",
      "url": "https://cdn8.zohanayaan.com:1686/hls/star1in.m3u8?md5=A1xJNgxmBZQ9e4gNk_Mz4A&expires=1782415223",
      "Referer": "https://executeandship.com/"
    },
    {
      "id": "starhindi",
      "title": "Star Sports 1 Hindi",
      "logo": "https://sm-live-tv-channel-logo.pages.dev/CricHD/Sports/1-exptv.png",
      "url": "https://cdn7.zohanayaan.com:1686/hls/starhindi.m3u8?md5=7-djimbtTZh-jg68uxxG5A&expires=1782415224",
      "Referer": "https://executeandship.com/"
    },
    {
      "id": "ptvpk",
      "title": "PTV Sports",
      "logo": "https://sm-live-tv-channel-logo.pages.dev/CricHD/Sports/20-exptv.png",
      "url": "https://cdn10.zohanayaan.com:1686/hls/ptvpk.m3u8?md5=sR4Dj0O1RXCA710Yi7M09A&expires=1782415224",
      "Referer": "https://executeandship.com/"
    },
    {
      "id": "willowusa",
      "title": "Willow HD",
      "logo": "https://sm-live-tv-channel-logo.pages.dev/CricHD/Sports/38-exptv.png",
      "url": "https://cdn4.zohanayaan.com:1686/hls/willowusa.m3u8?md5=Te09-ecUv_TLwi8gxiDa3Q&expires=1782415224",
      "Referer": "https://executeandship.com/"
    },
    {
      "id": "willowextra",
      "title": "Willow HD 2",
      "logo": "https://sm-live-tv-channel-logo.pages.dev/CricHD/Sports/8-exptv.png",
      "url": "https://cdn5.zohanayaan.com:1686/hls/willowextra.m3u8?md5=G2NkkhSN0pnc-Ejs56NmCA&expires=1782415225",
      "Referer": "https://executeandship.com/"
    },
    {
      "id": "tenspk",
      "title": "Ten Sports",
      "logo": "https://sm-live-tv-channel-logo.pages.dev/CricHD/Sports/10-exptv.png",
      "url": "https://cdn5.zohanayaan.com:1686/hls/tenspk.m3u8?md5=TRbUctpJvXYdYGFIklU_Xw&expires=1782415226",
      "Referer": "https://executeandship.com/"
    },
    {
      "id": "asportshd",
      "title": "A Sports HD",
      "logo": "https://sm-live-tv-channel-logo.pages.dev/CricHD/Sports/12-exptv.png",
      "url": "https://cdn2.zohanayaan.com:1686/hls/asportshd.m3u8?md5=JxiQTSY5GDvJc8sbeXvoHA&expires=1782415226",
      "Referer": "https://executeandship.com/"
    },
    {
      "id": "skyscric",
      "title": "Sky Sports Cricket",
      "logo": "https://sm-live-tv-channel-logo.pages.dev/CricHD/Sports/9-exptv.png",
      "url": "https://cdn9.zohanayaan.com:1686/hls/skyscric.m3u8?md5=IMpATnbOci7zHl--7Y5Hpg&expires=1782415227",
      "Referer": "https://executeandship.com/"
    },
    {
      "id": "skysme",
      "title": "Sky Cinema",
      "logo": "https://sm-live-tv-channel-logo.pages.dev/CricHD/Sports/skycinema.png",
      "url": "https://cdn9.zohanayaan.com:1686/hls/skysme.m3u8?md5=xdF2wVN4gdxMWyDJ6Kfy1g&expires=1782415227",
      "Referer": "https://executeandship.com/"
    },
    {
      "id": "bbtsp1",
      "title": "TNT 1",
      "logo": "https://sm-live-tv-channel-logo.pages.dev/CricHD/Sports/tnt.png",
      "url": "https://cdn3.zohanayaan.com:1686/hls/bbtsp1.m3u8?md5=v5fSkwitJSmCWubvWzAsow&expires=1782415228",
      "Referer": "https://executeandship.com/"
    },
    {
      "id": "bbtsp2",
      "title": "TNT 2",
      "logo": "https://sm-live-tv-channel-logo.pages.dev/CricHD/Sports/tnt.png",
      "url": "https://cdn9.zohanayaan.com:1686/hls/bbtsp2.m3u8?md5=i1xlJuly1czdbcUkDEZ2Og&expires=1782415229",
      "Referer": "https://executeandship.com/"
    },
    {
      "id": "bbtsp3",
      "title": "TNT 3",
      "logo": "https://sm-live-tv-channel-logo.pages.dev/CricHD/Sports/tnt.png",
      "url": "https://cdn6.zohanayaan.com:1686/hls/bbtsp3.m3u8?md5=okbvhlh_pFOMOxdtuqVFkA&expires=1782415229",
      "Referer": "https://executeandship.com/"
    },
    {
      "id": "bbtespn",
      "title": "TNT 4",
      "logo": "https://sm-live-tv-channel-logo.pages.dev/CricHD/Sports/tnt.png",
      "url": "https://cdn4.zohanayaan.com:1686/hls/bbtespn.m3u8?md5=bnkK8W2_vAd_tQtPDqz1KQ&expires=1782415230",
      "Referer": "https://executeandship.com/"
    },
    {
      "id": "sky1nz",
      "title": "Sky Sport Nz 1",
      "logo": "https://sm-live-tv-channel-logo.pages.dev/CricHD/Sports/56-exptv.png",
      "url": "https://cdn3.zohanayaan.com:1686/hls/sky1nz.m3u8?md5=NLQhsumtvVMFVK-6ZFzxIA&expires=1782415231",
      "Referer": "https://executeandship.com/"
    },
    {
      "id": "sky2nz",
      "title": "Sky Sport Nz 2",
      "logo": "https://sm-live-tv-channel-logo.pages.dev/CricHD/Sports/56-exptv.png",
      "url": "https://cdn9.zohanayaan.com:1686/hls/sky2nz.m3u8?md5=1xKnujS6CxH2JF6jxcfQDw&expires=1782415231",
      "Referer": "https://executeandship.com/"
    },
    {
      "id": "sky3nz",
      "title": "Sky Sport Nz 3",
      "logo": "https://sm-live-tv-channel-logo.pages.dev/CricHD/Sports/56-exptv.png",
      "url": "https://cdn4.zohanayaan.com:1686/hls/sky3nz.m3u8?md5=ZU0xWCEIuYWd0dSxcHB2Cw&expires=1782415231",
      "Referer": "https://executeandship.com/"
    },
    {
      "id": "sky4nz",
      "title": "Sky Sport Nz 4",
      "logo": "https://sm-live-tv-channel-logo.pages.dev/CricHD/Sports/56-exptv.png",
      "url": "https://cdn9.zohanayaan.com:1686/hls/sky4nz.m3u8?md5=lWn6ql2QRzuQjIgabUvYQQ&expires=1782415231",
      "Referer": "https://executeandship.com/"
    },
    {
      "id": "sky5nz",
      "title": "Sky Sport Nz 5",
      "logo": "https://sm-live-tv-channel-logo.pages.dev/CricHD/Sports/56-exptv.png",
      "url": "https://cdn6.zohanayaan.com:1686/hls/sky5nz.m3u8?md5=pOz_k7vC2rgKVH97Djq7sA&expires=1782415232",
      "Referer": "https://executeandship.com/"
    },
    {
      "id": "sky6nz",
      "title": "Sky Sport 6 Nz",
      "logo": "https://sm-live-tv-channel-logo.pages.dev/CricHD/Sports/56-exptv.png",
      "url": "https://cdn2.zohanayaan.com:1686/hls/sky6nz.m3u8?md5=SUoAFvQj7SkvG6DmytR-3w&expires=1782415232",
      "Referer": "https://executeandship.com/"
    },
    {
      "id": "sky7nz",
      "title": "Sky Sport Nz 7",
      "logo": "https://sm-live-tv-channel-logo.pages.dev/CricHD/Sports/56-exptv.png",
      "url": "https://cdn1.zohanayaan.com:1686/hls/sky7nz.m3u8?md5=knpN6EESGGKJZfV9S2e9-A&expires=1782415233",
      "Referer": "https://executeandship.com/"
    },
    {
      "id": "sky8nz",
      "title": "Sky Sport Nz 8",
      "logo": "https://sm-live-tv-channel-logo.pages.dev/CricHD/Sports/56-exptv.png",
      "url": "https://cdn9.zohanayaan.com:1686/hls/sky8nz.m3u8?md5=0Q-gIxUDJn_3rheJW3yeAQ&expires=1782415234",
      "Referer": "https://executeandship.com/"
    },
    {
      "id": "sky9nz",
      "title": "Sky Sport Nz 9",
      "logo": "https://sm-live-tv-channel-logo.pages.dev/CricHD/Sports/56-exptv.png",
      "url": "https://cdn9.zohanayaan.com:1686/hls/sky9nz.m3u8?md5=1UZ_OeoP83pHXYIJnb-4Mw&expires=1782415235",
      "Referer": "https://executeandship.com/"
    },
    {
      "id": "skysme",
      "title": "Sky Cinema",
      "logo": "https://sm-live-tv-channel-logo.pages.dev/CricHD/Sports/skycinema.png",
      "url": "https://cdn9.zohanayaan.com:1686/hls/skysme.m3u8?md5=xdF2wVN4gdxMWyDJ6Kfy1g&expires=1782415227",
      "Referer": "https://executeandship.com/"
    },
    {
      "id": "skysact",
      "title": "Sky Sports Action",
      "logo": "https://sm-live-tv-channel-logo.pages.dev/CricHD/Sports/1745007829332.png",
      "url": "https://cdn4.zohanayaan.com:1686/hls/skysact.m3u8?md5=rnSP1mmnRDX76yaJvDlFOQ&expires=1782415235",
      "Referer": "https://executeandship.com/"
    },
    {
      "id": "skysgol",
      "title": "Sky Sports Golf",
      "logo": "https://sm-live-tv-channel-logo.pages.dev/CricHD/Sports/1745008055327.png",
      "url": "https://cdn8.zohanayaan.com:1686/hls/skysgol.m3u8?md5=yAhGkv8P1RZW3TyWGUuqkQ&expires=1782415236",
      "Referer": "https://executeandship.com/"
    },
    {
      "id": "skysprem",
      "title": "Sky Sports Premier League",
      "logo": "https://sm-live-tv-channel-logo.pages.dev/CricHD/Sports/43-exptv.png",
      "url": "https://cdn3.zohanayaan.com:1686/hls/skysprem.m3u8?md5=LS8R53Ujm5jB8zzxl8C5Aw&expires=1782415236",
      "Referer": "https://executeandship.com/"
    },
    {
      "id": "skysfott",
      "title": "Sky Sports Football",
      "logo": "https://sm-live-tv-channel-logo.pages.dev/CricHD/Sports/44-exptv.png",
      "url": "https://cdn4.zohanayaan.com:1686/hls/skysfott.m3u8?md5=8lZA5MXER8K1mz3MKQcbaw&expires=1782415236",
      "Referer": "https://executeandship.com/"
    },
    {
      "id": "skysare",
      "title": "Sky Sports Arena",
      "logo": "https://sm-live-tv-channel-logo.pages.dev/CricHD/Sports/1745007829327.png",
      "url": "https://cdn3.zohanayaan.com:1686/hls/skysare.m3u8?md5=kiWwcdo7zX6RHaDaCu6cIw&expires=1782415236",
      "Referer": "https://executeandship.com/"
    },
    {
      "id": "skysfor1",
      "title": "Sky Sports F1",
      "logo": "https://sm-live-tv-channel-logo.pages.dev/CricHD/Sports/1745008468637.png",
      "url": "https://cdn10.zohanayaan.com:1686/hls/skysfor1.m3u8?md5=Bm9xy9-PzHlhxJITmQPYuQ&expires=1782415237",
      "Referer": "https://executeandship.com/"
    },
    {
      "id": "laligauk",
      "title": "LaLiGA",
      "logo": "https://sm-live-tv-channel-logo.pages.dev/CricHD/Sports/19-exptv.png",
      "url": "https://cdn4.zohanayaan.com:1686/hls/laligauk.m3u8?md5=VUXLbFofg4nT2HAMW740Ow&expires=1782415237",
      "Referer": "https://executeandship.com/"
    },
    {
      "id": "premieruk",
      "title": "Premier Sports 1",
      "logo": "https://sm-live-tv-channel-logo.pages.dev/CricHD/Sports/31-exptv.png",
      "url": "https://cdn10.zohanayaan.com:1686/hls/premieruk.m3u8?md5=rYya4uLu4zXHKyRWlwQVgg&expires=1782415237",
      "Referer": "https://executeandship.com/"
    },
    {
      "id": "hdchnl2",
      "title": "Premier Sports 2",
      "logo": "https://sm-live-tv-channel-logo.pages.dev/CricHD/Sports/31-exptv.png",
      "url": "https://cdn6.zohanayaan.com:1686/hls/hdchnl2.m3u8?md5=WJL7_3-1H5y4Sf4cbBrXAQ&expires=1782415238",
      "Referer": "https://executeandship.com/"
    },
    {
      "id": "superfotball",
      "title": "Super Football",
      "logo": "https://sm-live-tv-channel-logo.pages.dev/CricHD/Sports/34-exptv.png",
      "url": "https://cdn4.zohanayaan.com:1686/hls/superfotball.m3u8?md5=_OOEocnLFuxKgXvEiHD6Bg&expires=1782415238",
      "Referer": "https://executeandship.com/"
    },
    {
      "id": "superpremier",
      "title": "Super Premier League",
      "logo": "https://sm-live-tv-channel-logo.pages.dev/CricHD/Sports/1745008781606.png",
      "url": "https://cdn1.zohanayaan.com:1686/hls/superpremier.m3u8?md5=3_mS53j_QU-3Nd1X17zGOQ&expires=1782415238",
      "Referer": "https://executeandship.com/"
    },
    {
      "id": "fox501",
      "title": "Fox Cricket 501 HD",
      "logo": "https://sm-live-tv-channel-logo.pages.dev/CricHD/Sports/6-exptv.png",
      "url": "https://cdn5.zohanayaan.com:1686/hls/fox501.m3u8?md5=0ZAUxERtMtsXYv4EJTJiQA&expires=1782415239",
      "Referer": "https://executeandship.com/"
    },
    {
      "id": "espnusa",
      "title": "ESPN 1",
      "logo": "https://sm-live-tv-channel-logo.pages.dev/CricHD/Sports/17-exptv.png",
      "url": "https://cdn3.zohanayaan.com:1686/hls/espnusa.m3u8?md5=S43Xv8Ka-LpYep73metNfQ&expires=1782415239",
      "Referer": "https://executeandship.com/"
    },
    {
      "id": "espn2",
      "title": "ESPN 2",
      "logo": "https://sm-live-tv-channel-logo.pages.dev/CricHD/Sports/17-exptv.png",
      "url": "https://cdn6.zohanayaan.com:1686/hls/espn2.m3u8?md5=gHDPuyvX2mgInxOPCD8AKQ&expires=1782415239",
      "Referer": "https://executeandship.com/"
    },
    {
      "id": "skysare",
      "title": "Sky Sports Arena",
      "logo": "https://sm-live-tv-channel-logo.pages.dev/CricHD/Sports/1745007829327.png",
      "url": "https://cdn3.zohanayaan.com:1686/hls/skysare.m3u8?md5=kiWwcdo7zX6RHaDaCu6cIw&expires=1782415236",
      "Referer": "https://executeandship.com/"
    },
    {
      "id": "skysmixx",
      "title": "Sky Sports Mix",
      "logo": "https://sm-live-tv-channel-logo.pages.dev/CricHD/Sports/13-exptv.png",
      "url": "https://cdn10.zohanayaan.com:1686/hls/skysmixx.m3u8?md5=qx1Af-Rh3mOyGLfefSn_8A&expires=1782415240",
      "Referer": "https://executeandship.com/"
    },
    {
      "id": "skystennis",
      "title": "Sky Sports Tennis",
      "logo": "https://sm-live-tv-channel-logo.pages.dev/CricHD/Sports/1745009085794.png",
      "url": "https://cdn5.zohanayaan.com:1686/hls/skystennis.m3u8?md5=sQy0FqQfbD0LTi9svBlnNw&expires=1782415241",
      "Referer": "https://executeandship.com/"
    },
    {
      "id": "fox501",
      "title": "Fox Cricket 501 HD",
      "logo": "https://sm-live-tv-channel-logo.pages.dev/CricHD/Sports/6-exptv.png",
      "url": "https://cdn5.zohanayaan.com:1686/hls/fox501.m3u8?md5=0ZAUxERtMtsXYv4EJTJiQA&expires=1782415239",
      "Referer": "https://executeandship.com/"
    },
    {
      "id": "ten1hd",
      "title": "Sony Sports3",
      "logo": "https://sm-live-tv-channel-logo.pages.dev/CricHD/Sports/1000173192-modified.png",
      "url": "https://cdn8.zohanayaan.com:1686/hls/ten1hd.m3u8?md5=_iSwu6UrTSJen1T6vJwVMA&expires=1782415242",
      "Referer": "https://executeandship.com/"
    }
  ]
}